quapp_pennylane/__init__.py
quapp_pennylane/async_tasks/__init__.py
quapp_pennylane/async_tasks/pennylane_circuit_export_task.py
quapp_pennylane/component/__init__.py
quapp_pennylane/component/backend/__init__.py
quapp_pennylane/component/backend/pennylane_invocation.py
quapp_pennylane/factory/__init__.py
quapp_pennylane/factory/pennylane_device_factory.py
quapp_pennylane/factory/pennylane_handler_factory.py
quapp_pennylane/factory/pennylane_provider_factory.py
quapp_pennylane/handler/__init__.py
quapp_pennylane/handler/invocation_handler.py
quapp_pennylane/model/__init__.py
quapp_pennylane/model/device/__init__.py
quapp_pennylane/model/device/aws_braket_device.py
quapp_pennylane/model/device/ibm_quantum_device.py
quapp_pennylane/model/device/pennylane_device.py
quapp_pennylane/model/device/qapp_pennylane_device.py
quapp_pennylane/model/provider/__init__.py
quapp_pennylane/model/provider/aws_braket_provider.py
quapp_pennylane/model/provider/ibm_cloud_provider.py
quapp_pennylane/model/provider/ibm_quantum_provider.py
quapp_pennylane/model/provider/qapp_pennylane_provider.py
quapp_pennylane-0.0.4.dev7.dist-info/licenses/LICENSE
quapp_pennylane-0.0.4.dev7.dist-info/METADATA
quapp_pennylane-0.0.4.dev7.dist-info/WHEEL
quapp_pennylane-0.0.4.dev7.dist-info/top_level.txt
quapp_pennylane-0.0.4.dev7.dist-info/RECORD
