Metadata-Version: 2.4
Name: quapp-pennylane
Version: 0.0.4.dev7
Summary: Quapp pennylane library supporting Quapp Platform for Quantum Computing
Author-email: "CITYNOW Co. Ltd. " <corp@citynow.vn>
License: The MIT License (MIT)
Project-URL: Homepage, https://citynow.asia/
Keywords: quapp,quapp-pennylane,pennylane,quantum
Classifier: License :: OSI Approved :: MIT License
Classifier: Programming Language :: Python
Classifier: Programming Language :: Python :: 3
Requires-Python: >=3.10
License-File: LICENSE
Requires-Dist: quapp-common==0.0.11.dev7
Requires-Dist: autoray==0.6.11
Requires-Dist: pennylane==0.37.0
Requires-Dist: matplotlib
Requires-Dist: PennyLane-Rigetti==0.36.0
Requires-Dist: PennyLane_Lightning==0.37.0
Provides-Extra: dev
Requires-Dist: black; extra == "dev"
Requires-Dist: bumpver; extra == "dev"
Requires-Dist: isort; extra == "dev"
Requires-Dist: pip-tools; extra == "dev"
Requires-Dist: pytest; extra == "dev"
Dynamic: license-file
